fivbvis/__init__.py
fivbvis/fivbvis.py
fivbvis/references.py
fivbvis/version.py
fivbvis-0.3.dist-info/LICENSE.md
fivbvis-0.3.dist-info/METADATA
fivbvis-0.3.dist-info/WHEEL
fivbvis-0.3.dist-info/top_level.txt
fivbvis-0.3.dist-info/RECORD
