Metadata-Version: 2.1
Name: fivbvis
Version: 0.3
Summary: Python client for the Volleyball Information System (FIVB VIS)
Home-page: https://github.com/claromes/fivbvis
Author: Claromes
Author-email: support@claromes.com
License: GPLv3
Project-URL: Documentation, https://github.com/claromes/fivbvis/blob/main/docs/documentation.md
Project-URL: Bug Tracker, https://github.com/claromes/fivbvis/issues
Project-URL: Releases, https://github.com/claromes/fivbvis/releases
Keywords: fivbvis fivb volleyball beachvolleyball sports datasets analytics
Classifier: Development Status :: 4 - Beta
Classifier: Intended Audience :: Science/Research
Classifier: Intended Audience :: Other Audience
Classifier: License :: OSI Approved :: GNU General Public License v3 (GPLv3)
Classifier: Programming Language :: Python :: 3.8
Classifier: Programming Language :: Python :: 3.11
Classifier: Topic :: Scientific/Engineering
Classifier: Topic :: Software Development
Classifier: Topic :: Software Development :: Libraries :: Python Modules
Classifier: Topic :: Utilities
Requires-Python: >=3.8
License-File: LICENSE.md
Requires-Dist: httpx ==0.26.0
